{"id":1107991,"parent_id":null,"name":1107991,"style":null,"slug":1107991,"version":1,"description":"feel free to take the idea, i don't care. i don't have the imagination to continue (\u00b4\u30fb\u03c9\u30fb\uff40)","public":1,"allow_clone":1,"download_count":7,"owner_id":502407,"modified":"2018-08-11 19:23:45","generated_at":null,"active":1,"deleted":0,"license_id":3,"brick_scale_x":2,"brick_scale_y":2,"grid_scale_x":1,"grid_scale_y":1,"created":"2015-01-29 08:33:28","comment_count":3,"vote_count":3,"vote_total":30,"rating":10,"spacing":0,"fixed_width":0,"glyph_count":11,"published":"2015-01-30 22:12:06","flash_optimized":1,"is_fixed":0,"weighted_rating":8.6698900000000005,"close_comments":0,"edited":"2015-03-14 03:09:48","favorite_count":2,"pop_pick_count":0,"force_private":0,"ascender":null,"descender":null,"auto_ascender":1,"auto_descender":1,"layers":[{"id":1098104,"name":"Layer-1","color":"FF0000","rgb":0,"visible":1,"locked":0,"sort_order":1}],"glyphs":[{"id":27088470,"codepoint":65,"rsb":null,"glyph_layers":[{"idx":0,"nodes":[{"br":15,"x":1,"y":2},{"br":15,"x":2,"y":4},{"br":15,"x":3,"y":6},{"br":16,"x":7,"y":0},{"br":9,"x":1,"y":9,"tx":500},{"br":1,"x":7,"y":9},{"br":22,"x":2,"y":1,"tx":-500},{"br":22,"x":4,"y":0,"tx":-500},{"br":15,"x":0,"y":0},{"br":7,"x":6,"y":0,"tx":-500},{"br":16,"x":1,"y":7,"tx":500},{"br":6,"x":3,"y":4},{"br":6,"x":5,"y":4},{"br":2,"x":7,"y":7},{"br":2,"x":7,"y":5},{"br":2,"x":7,"y":3},{"br":2,"x":7,"y":2},{"br":25,"x":4,"y":8},{"br":9,"x":5,"y":9,"tx":-500},{"br":0,"x":0,"y":2},{"br":8,"x":3,"y":9,"tx":500}],"layer_id":1098104}]},{"id":27127756,"codepoint":75,"rsb":10,"glyph_layers":[{"idx":1,"nodes":[{"br":0,"x":0,"y":9},{"br":1,"x":1,"y":8},{"br":1,"x":3,"y":9},{"br":2,"x":1,"y":6},{"br":19,"x":3,"y":6},{"br":2,"x":1,"y":4},{"br":3,"x":0,"y":0},{"br":0,"x":0,"y":6},{"br":0,"x":0,"y":4},{"br":4,"x":0,"y":2},{"br":4,"x":2,"y":2},{"br":3,"x":2,"y":0},{"br":5,"x":3,"y":0},{"br":4,"x":2,"y":7},{"br":2,"x":3,"y":4},{"br":7,"x":2,"y":10},{"br":7,"x":5,"y":0},{"br":8,"x":7,"y":7},{"br":20,"x":5,"y":7},{"br":21,"x":5,"y":4},{"br":21,"x":6,"y":2},{"br":21,"x":7,"y":0},{"br":7,"x":7,"y":2},{"br":7,"x":6,"y":4}],"layer_id":1098104}]},{"id":27127757,"codepoint":76,"rsb":null,"glyph_layers":[{"idx":2,"nodes":[{"br":0,"x":0,"y":9},{"br":1,"x":1,"y":8},{"br":1,"x":3,"y":9},{"br":2,"x":1,"y":6},{"br":2,"x":3,"y":6},{"br":2,"x":1,"y":4},{"br":3,"x":0,"y":0},{"br":0,"x":0,"y":6},{"br":0,"x":0,"y":4},{"br":4,"x":0,"y":2},{"br":4,"x":2,"y":2},{"br":3,"x":2,"y":0},{"br":5,"x":3,"y":0},{"br":6,"x":5,"y":0},{"br":4,"x":2,"y":7},{"br":7,"x":7,"y":0},{"br":7,"x":3,"y":7},{"br":2,"x":3,"y":4},{"br":7,"x":3,"y":5},{"br":7,"x":2,"y":10}],"layer_id":1098104}]},{"id":27127781,"codepoint":97,"rsb":null,"glyph_layers":[{"idx":3,"nodes":[{"br":31,"x":0,"y":0},{"br":9,"x":0,"y":3},{"br":20,"x":1,"y":6},{"br":8,"x":3,"y":6},{"br":4,"x":3,"y":4},{"br":4,"x":3,"y":2},{"br":16,"x":4,"y":0},{"br":22,"x":2,"y":3},{"br":1,"x":4,"y":6},{"br":20,"x":2,"y":0},{"br":21,"x":0,"y":5},{"br":32,"x":4,"y":1}],"layer_id":1098104}]},{"id":27127764,"codepoint":105,"rsb":3,"glyph_layers":[{"idx":4,"nodes":[{"br":17,"x":0,"y":5},{"br":4,"x":0,"y":4},{"br":1,"x":1,"y":6},{"br":16,"x":1,"y":0},{"br":4,"x":0,"y":2},{"br":26,"x":2,"y":9},{"br":27,"x":0,"y":9}],"layer_id":1098104}]},{"id":27127791,"codepoint":106,"rsb":3,"glyph_layers":[{"idx":5,"nodes":[{"br":17,"x":0,"y":5},{"br":4,"x":0,"y":4},{"br":1,"x":1,"y":6},{"br":4,"x":0,"y":2},{"br":26,"x":2,"y":9},{"br":27,"x":0,"y":9},{"br":4,"x":0,"y":0},{"br":4,"x":0,"y":-1},{"br":3,"x":0,"y":-3},{"br":16,"x":1,"y":-2}],"layer_id":1098104}]},{"id":27127765,"codepoint":108,"rsb":null,"glyph_layers":[{"idx":6,"nodes":[{"br":17,"x":0,"y":8},{"br":4,"x":0,"y":7},{"br":1,"x":1,"y":9},{"br":4,"x":0,"y":5},{"br":4,"x":0,"y":3},{"br":4,"x":0,"y":2},{"br":16,"x":1,"y":0}],"layer_id":1098104}]},{"id":27127766,"codepoint":109,"rsb":null,"glyph_layers":[{"idx":7,"nodes":[{"br":17,"x":0,"y":6},{"br":4,"x":0,"y":4},{"br":9,"x":1,"y":6},{"br":16,"x":1,"y":0},{"br":4,"x":0,"y":2},{"br":17,"x":3,"y":6},{"br":4,"x":3,"y":4},{"br":9,"x":4,"y":6},{"br":16,"x":4,"y":0},{"br":4,"x":3,"y":2},{"br":17,"x":6,"y":6},{"br":4,"x":6,"y":4},{"br":16,"x":7,"y":0},{"br":4,"x":6,"y":2},{"br":18,"x":4,"y":4},{"br":18,"x":4,"y":2},{"br":18,"x":1,"y":4},{"br":18,"x":1,"y":2}],"layer_id":1098104}]},{"id":27127758,"codepoint":111,"rsb":7,"glyph_layers":[{"idx":8,"nodes":[{"br":1,"x":0,"y":6},{"br":8,"x":4,"y":6},{"br":9,"x":2,"y":6},{"br":2,"x":0,"y":4},{"br":2,"x":0,"y":2},{"br":16,"x":0,"y":0},{"br":11,"x":4,"y":0},{"br":4,"x":4,"y":2},{"br":4,"x":4,"y":4},{"br":12,"x":2,"y":4},{"br":12,"x":2,"y":2},{"br":5,"x":2,"y":0}],"layer_id":1098104}]},{"id":27127759,"codepoint":115,"rsb":6,"glyph_layers":[{"idx":9,"nodes":[{"br":9,"x":0,"y":6},{"br":30,"x":3,"y":6},{"br":29,"x":0,"y":0},{"br":11,"x":3,"y":0},{"br":15,"x":2,"y":4},{"br":16,"x":0,"y":4},{"br":17,"x":3,"y":2},{"br":15,"x":1,"y":2},{"br":5,"x":0,"y":2},{"br":18,"x":3,"y":4},{"br":18,"x":3,"y":8}],"layer_id":1098104}]},{"id":27127790,"codepoint":122,"rsb":null,"glyph_layers":[{"idx":10,"nodes":[{"br":0,"x":0,"y":6},{"br":22,"x":2,"y":6},{"br":20,"x":4,"y":6},{"br":20,"x":0,"y":0},{"br":22,"x":2,"y":0},{"br":7,"x":4,"y":0},{"br":15,"x":4,"y":5},{"br":15,"x":0,"y":1},{"br":15,"x":3,"y":3},{"br":15,"x":1,"y":3}],"layer_id":1098104}]}],"palette_slots":[{"id":14978285,"pos":1,"order":1,"brick_id":258,"composites":[]},{"id":14978286,"pos":2,"order":2,"brick_id":251,"composites":[]},{"id":14978287,"pos":3,"order":3,"brick_id":143,"composites":[]},{"id":14978288,"pos":4,"order":4,"brick_id":253,"composites":[]},{"id":14978289,"pos":5,"order":5,"brick_id":141,"composites":[]},{"id":14978290,"pos":6,"order":6,"brick_id":254,"composites":[]},{"id":14978291,"pos":7,"order":7,"brick_id":142,"composites":[]},{"id":14978292,"pos":8,"order":8,"brick_id":256,"composites":[]},{"id":14978293,"pos":9,"order":9,"brick_id":208,"composites":[]},{"id":14978294,"pos":10,"order":10,"brick_id":207,"composites":[]},{"id":14978296,"pos":12,"order":11,"brick_id":209,"composites":[]},{"id":14978297,"pos":13,"order":12,"brick_id":0,"composites":[{"id":11535888,"palette_slot_id":14978297,"brick_id":143,"tx":0,"ty":0,"w":1,"h":1},{"id":11535889,"palette_slot_id":14978297,"brick_id":252,"tx":0,"ty":0,"w":1,"h":1}]},{"id":14978300,"pos":16,"order":13,"brick_id":187,"composites":[]},{"id":14978301,"pos":17,"order":14,"brick_id":257,"composites":[]},{"id":14978302,"pos":18,"order":15,"brick_id":255,"composites":[]},{"id":14978303,"pos":19,"order":16,"brick_id":252,"composites":[]},{"id":14978304,"pos":20,"order":17,"brick_id":0,"composites":[{"id":11535894,"palette_slot_id":14978304,"brick_id":143,"tx":0,"ty":0,"w":1,"h":1},{"id":11535895,"palette_slot_id":14978304,"brick_id":189,"tx":0,"ty":0,"w":1,"h":1}]},{"id":14978305,"pos":21,"order":18,"brick_id":189,"composites":[]},{"id":14978306,"pos":22,"order":19,"brick_id":190,"composites":[]},{"id":14978307,"pos":23,"order":20,"brick_id":188,"composites":[]},{"id":14978308,"pos":26,"order":21,"brick_id":0,"composites":[{"id":11535896,"palette_slot_id":14978308,"brick_id":152,"tx":1,"ty":1,"w":2,"h":2},{"id":11535897,"palette_slot_id":14978308,"brick_id":160,"tx":0,"ty":1,"w":2,"h":2}]},{"id":14978317,"pos":27,"order":22,"brick_id":116,"composites":[]},{"id":14978318,"pos":28,"order":23,"brick_id":118,"composites":[]},{"id":14978331,"pos":30,"order":24,"brick_id":0,"composites":[{"id":11535901,"palette_slot_id":14978331,"brick_id":229,"tx":0,"ty":0,"w":1,"h":1},{"id":11535902,"palette_slot_id":14978331,"brick_id":254,"tx":0,"ty":0,"w":1,"h":1}]},{"id":14978332,"pos":31,"order":25,"brick_id":0,"composites":[{"id":11535903,"palette_slot_id":14978332,"brick_id":227,"tx":0,"ty":0,"w":1,"h":1},{"id":11535904,"palette_slot_id":14978332,"brick_id":252,"tx":0,"ty":0,"w":1,"h":1}]},{"id":14978337,"pos":32,"order":26,"brick_id":210,"composites":[]},{"id":14978338,"pos":33,"order":27,"brick_id":0,"composites":[{"id":11535906,"palette_slot_id":14978338,"brick_id":173,"tx":0,"ty":1,"w":2,"h":2}]}],"brick_set":{"bricks":[{"id":258,"name":"Thorn 8","contours":"M 1000 500 L 1000 0 Q 585.4226519337 -0 292.625 293 0 585.82722874914 0 1000 Q 0 792.91361437457 292.625 646.5 585.4226519337 500 1000 500","cubic":"M 1000 500 L 1000 0 C 447 0 0 448 0 1000 C 0 724 447 500 1000 500"},{"id":251,"name":"Thorn 1","contours":"M 1000 0 Q 585.82722874914 -0 293 292.625 0 585.4226519337 0 1000 L 500 1000 Q 500 585.4226519337 646.5 292.625 792.91361437457 0 1000 0","cubic":"M 1000 0 C 448 0 0 447 0 1000 L 500 1000 C 500 447 724 0 1000 0"},{"id":143,"name":"Double Quarter Square 4","contours":"M 0 0 L 500 0 L 500 1000 L 0 1000 L 0 0","cubic":"M 0 1000 L 500 1000 L 500 0 L 0 0 L 0 1000"},{"id":253,"name":"Thorn 3","contours":"M 0 1000 Q 414.17277125086 1000 707 707.375 1000 414.5773480663 1000 0 L 500 0 Q 500 414.5773480663 353.5 707.375 207.08638562543 1000 0 1000","cubic":"M 0 1000 C 552 1000 1000 553 1000 0 L 500 0 C 500 553 276 1000 0 1000"},{"id":141,"name":"Double Quarter Square 2","contours":"M 500 0 L 1000 0 L 1000 1000 L 500 1000 L 500 0","cubic":"M 500 1000 L 1000 1000 L 1000 0 L 500 0 L 500 1000"},{"id":254,"name":"Thorn 4","contours":"M 0 0 Q -0 414.17277125086 292.625 707 585.4226519337 1000 1000 1000 L 1000 500 Q 585.4226519337 500 292.625 353.5 0 207.08638562543 0 0","cubic":"M 0 0 C 0 552 447 1000 1000 1000 L 1000 500 C 447 500 0 276 0 0"},{"id":142,"name":"Double Quarter Square 3","contours":"M 0 500 L 1000 500 L 1000 1000 L 0 1000 L 0 500","cubic":"M 0 1000 L 1000 1000 L 1000 500 L 0 500 L 0 1000"},{"id":256,"name":"Thorn 6","contours":"M 0 500 L 0 1000 Q 414.5773480663 1000 707.375 707 1000 414.17277125086 1000 0 Q 1000 207.08638562543 707.375 353.5 414.5773480663 500 0 500","cubic":"M 0 500 L 0 1000 C 553 1000 1000 552 1000 0 C 1000 276 553 500 0 500"},{"id":208,"name":"Quarter Ring 2","contours":"M 0 500 Q 207 500 353 647 500 793 500 1000 L 1000 1000 Q 1000 586 707 293 414 0 0 0 L 0 500","cubic":"M 0 500 C 276 500 499 724 500 1000 L 1000 1000 C 1000 448 552 0 0 0 L 0 500"},{"id":207,"name":"Quarter Ring 1","contours":"M 500 1000 Q 500 793 647 647 793 500 1000 500 L 1000 0 Q 586 0 293 293 0 586 0 1000 L 500 1000","cubic":"M 500 1000 C 501 724 724 501 1000 500 L 1000 0 C 448 0 0 448 0 1000 L 500 1000"},{"id":209,"name":"Quarter Ring 3","contours":"M 500 0 Q 500 207 353 353 207 500 0 500 L 0 1000 Q 414 1000 707 707 1000 414 1000 0 L 500 0","cubic":"M 500 0 C 499 276 276 499 0 500 L 0 1000 C 552 1000 1000 552 1000 0 L 500 0"},{"id":252,"contours":"M 1000 1000 Q 1000 585.82722874914 707.375 293 414.5773480663 -0 0 0 L 0 500 Q 414.5773480663 500 707.375 646.5 1000 792.91361437457 1000 1000","cubic":"M 1000 1000 C 1000 448 553 0 0 0 L 0 500 C 553 500 1000 724 1000 1000"},{"id":187,"name":"Diagonal 1","contours":"M 500 0 L 0 1000 L 500 1000 L 1000 0 L 500 0","cubic":"M 500 0 L 0 1000 L 500 1000 L 1000 0 L 500 0"},{"id":257,"name":"Thorn 7","contours":"M 500 0 L 0 0 Q -0 414.5773480663 293 707.375 585.82722874914 1000 1000 1000 Q 792.91361437457 1000 646.5 707.375 500 414.5773480663 500 0","cubic":"M 500 0 L 0 0 C 0 553 448 1000 1000 1000 C 724 1000 500 553 500 0"},{"id":255,"name":"Thorn 5","contours":"M 500 1000 L 1000 1000 Q 1000 585.4226519337 707 292.625 414.17277125086 -0 0 0 Q 207.08638562543 0 353.5 292.625 500 585.4226519337 500 1000","cubic":"M 500 1000 L 1000 1000 C 1000 447 552 0 0 0 C 276 0 500 447 500 1000"},{"id":189,"contours":"M 1000 0 L 0 500 L 0 1000 L 1000 500 L 1000 0","cubic":"M 1000 0 L 0 500 L 0 1000 L 1000 500 L 1000 0"},{"id":190,"name":"Diagonal 4","contours":"M 1000 1000 L 500 0 L 0 0 L 500 1000 L 1000 1000","cubic":"M 1000 1000 L 500 0 L 0 0 L 500 1000 L 1000 1000"},{"id":188,"name":"Diagonal 2","contours":"M 1000 500 L 0 0 L 0 500 L 1000 1000 L 1000 500","cubic":"M 1000 500 L 0 0 L 0 500 L 1000 1000 L 1000 500"},{"id":152,"contours":"M 500 0 L 0 0 L 0 1000 L 500 0","cubic":"M 500 0 L 0 0 L 0 1000 L 500 0"},{"id":160,"contours":"M 1000 1000 L 1000 0 L 500 0 L 0 1000 L 1000 1000","cubic":"M 1000 1000 L 1000 0 L 500 0 L 0 1000 L 1000 1000"},{"id":116,"name":"Single Square Quarter 1","contours":"M 500 500 L 0 0 L 0 1000 L 500 500","cubic":"M 500 500 L 0 0 L 0 1000 L 500 500"},{"id":118,"name":"Single Square Quarter 3","contours":"M 500 500 L 1000 1000 L 1000 0 L 500 500","cubic":"M 500 500 L 1000 1000 L 1000 0 L 500 500"},{"id":229,"contours":"M 1000 0 L 500 0 L 0 1000 L 1000 0","cubic":"M 1000 0 L 500 0 L 0 1000 L 1000 0"},{"id":227,"contours":"M 0 1000 L 500 1000 L 1000 0 L 0 1000","cubic":"M 0 1000 L 500 1000 L 1000 0 L 0 1000"},{"id":210,"name":"Quarter Ring 4","contours":"M 1000 500 Q 793 500 647 353 500 207 500 0 L 0 0 Q 0 414 293 707 586 1000 1000 1000 L 1000 500","cubic":"M 1000 500 C 724 500 501 276 500 0 L 0 0 C 0 552 448 1000 1000 1000 L 1000 500"},{"id":173,"contours":"M 0 1000 L 1000 500 L 1000 0 L 0 0 L 0 1000","cubic":"M 0 1000 L 1000 500 L 1000 0 L 0 0 L 0 1000"}]}}